Workbook

Sheet Instructions
B2: AS9100D Gap Assessment Workbook
B3: Clauses 4–10 | Aerospace, space and defense | Field tool for readiness assessments | Version 1.0, October 2026
B5: How to use
B6: 1. Set up | C6: Enter the client, site or scope, auditor and date on the Summary sheet. Decide the boundary first: one process, one department or one site.
B7: 2. Assess | C7: On the Checklist sheet, work clause by clause. Ask the audit question, request the evidence listed, compare what you see with the common findings, and use the follow-up question to test depth.
B8: 3. Record | C8: Fill the shaded cream cells only: Status (dropdown), Evidence seen / notes, Owner, Target date.
B9: 4. Review | C9: The Summary sheet updates automatically from your statuses, by clause and by requirement source.
B10: 5. Act | C10: Turn every gap into an action with an owner and a date, and re-assess after closure to confirm the gap is really gone.
B11: Status values | C11: Conforming | Minor gap | Major gap | Not applicable (justify in notes) | Not assessed (default)
B12: Legend | C12: Shaded cream cells = your input. Everything else is reference content or formulas.
B13: Source column | C13: ISO 9001 base = requirement that exists in ISO 9001:2015. AS9100D addition = aerospace-specific requirement. Mixed = the row combines both. Use it to separate a basic ISO 9001 weakness from an aerospace-specific gap.
B14: Related IAQG docs | C14: Lists IAQG 9100-series documents that support the clause (for example 9102 first article inspection, 9103 key characteristics). Taken from the standard's own cross-reference annex. They are supporting documents; check whether the customer contract makes them mandatory.
B15: Which standard? | C15: This workbook is for organizations that design, develop or produce aviation, space and defense products. Maintenance organizations use 9110, distributors use 9120, and deliverable software is covered by 9115 in addition to 9100.
B16: Edition note | C16: Based on AS9100 Rev D (September 2016). The IAQG is revising the 9100 series (to be published as IA9100). Check which edition your customer and certification body apply, and treat this workbook as a basis for the current edition.
B17: Important | C17: Clause text is paraphrased for field use and is not a reproduction of the standard. AS9100D is copyrighted by SAE International and the IAQG, and includes ISO 9001:2015 text used with ISO permission. Always verify requirements against the licensed standard. This workbook supports, and does not replace, auditor judgment. Findings are indicative, not a certification decision.
B18: AI-assisted use | C18: See the AI Use Guide sheet for where AI helps, what to keep out of it (including export-controlled data), and starter prompts.
B20: Example of a completed row
B21: Ref / Clause | C21: 8.4.1.1 Provider approval status and register
B22: Status | C22: Minor gap
B23: Evidence seen / notes | C23: Approved provider register reviewed; 4 of 60 active providers have no approval scope recorded. 1 of 5 sampled purchase orders (PO 1042) placed with a provider marked conditional, no documented release for the conditional use. Customer-designated source list not cross-checked against the register.
B24: Owner | C24: Purchasing Manager
B25: Target date | C25: 2026-12-15
B27: © 2026 Cristian La Bella Consulting. All rights reserved. | cristianlabella.com

Sheet Summary
B2: Assessment Summary
B4: Client
B5: Site / scope
B6: Auditor
B7: Assessment date
B9: Clause | C9: Items | D9: Conforming | E9: Minor gap | F9: Major gap | G9: Not applicable | H9: Not assessed | I9: Conformity %
B10: 4 Context of the organization | C10: =COUNTIF(Checklist!$N$2:$N$89,4) -> 5 | D10: =COUNTIFS(Checklist!$N$2:$N$89,4,Checklist!$J$2:$J$89,"Conforming") -> 0 | E10: =COUNTIFS(Checklist!$N$2:$N$89,4,Checklist!$J$2:$J$89,"Minor gap") -> 0 | F10: =COUNTIFS(Checklist!$N$2:$N$89,4,Checklist!$J$2:$J$89,"Major gap") -> 0 | G10: =COUNTIFS(Checklist!$N$2:$N$89,4,Checklist!$J$2:$J$89,"Not applicable") -> 0 | H10: =COUNTIFS(Checklist!$N$2:$N$89,4,Checklist!$J$2:$J$89,"Not assessed") -> 5 | I10: =IF((C10-G10-H10)=0,"n/a",D10/(C10-G10-H10)) -> n/a
B11: 5 Leadership | C11: =COUNTIF(Checklist!$N$2:$N$89,5) -> 5 | D11: =COUNTIFS(Checklist!$N$2:$N$89,5,Checklist!$J$2:$J$89,"Conforming") -> 0 | E11: =COUNTIFS(Checklist!$N$2:$N$89,5,Checklist!$J$2:$J$89,"Minor gap") -> 0 | F11: =COUNTIFS(Checklist!$N$2:$N$89,5,Checklist!$J$2:$J$89,"Major gap") -> 0 | G11: =COUNTIFS(Checklist!$N$2:$N$89,5,Checklist!$J$2:$J$89,"Not applicable") -> 0 | H11: =COUNTIFS(Checklist!$N$2:$N$89,5,Checklist!$J$2:$J$89,"Not assessed") -> 5 | I11: =IF((C11-G11-H11)=0,"n/a",D11/(C11-G11-H11)) -> n/a
B12: 6 Planning | C12: =COUNTIF(Checklist!$N$2:$N$89,6) -> 5 | D12: =COUNTIFS(Checklist!$N$2:$N$89,6,Checklist!$J$2:$J$89,"Conforming") -> 0 | E12: =COUNTIFS(Checklist!$N$2:$N$89,6,Checklist!$J$2:$J$89,"Minor gap") -> 0 | F12: =COUNTIFS(Checklist!$N$2:$N$89,6,Checklist!$J$2:$J$89,"Major gap") -> 0 | G12: =COUNTIFS(Checklist!$N$2:$N$89,6,Checklist!$J$2:$J$89,"Not applicable") -> 0 | H12: =COUNTIFS(Checklist!$N$2:$N$89,6,Checklist!$J$2:$J$89,"Not assessed") -> 5 | I12: =IF((C12-G12-H12)=0,"n/a",D12/(C12-G12-H12)) -> n/a
B13: 7 Support | C13: =COUNTIF(Checklist!$N$2:$N$89,7) -> 15 | D13: =COUNTIFS(Checklist!$N$2:$N$89,7,Checklist!$J$2:$J$89,"Conforming") -> 0 | E13: =COUNTIFS(Checklist!$N$2:$N$89,7,Checklist!$J$2:$J$89,"Minor gap") -> 0 | F13: =COUNTIFS(Checklist!$N$2:$N$89,7,Checklist!$J$2:$J$89,"Major gap") -> 0 | G13: =COUNTIFS(Checklist!$N$2:$N$89,7,Checklist!$J$2:$J$89,"Not applicable") -> 0 | H13: =COUNTIFS(Checklist!$N$2:$N$89,7,Checklist!$J$2:$J$89,"Not assessed") -> 15 | I13: =IF((C13-G13-H13)=0,"n/a",D13/(C13-G13-H13)) -> n/a
B14: 8 Operation | C14: =COUNTIF(Checklist!$N$2:$N$89,8) -> 46 | D14: =COUNTIFS(Checklist!$N$2:$N$89,8,Checklist!$J$2:$J$89,"Conforming") -> 0 | E14: =COUNTIFS(Checklist!$N$2:$N$89,8,Checklist!$J$2:$J$89,"Minor gap") -> 0 | F14: =COUNTIFS(Checklist!$N$2:$N$89,8,Checklist!$J$2:$J$89,"Major gap") -> 0 | G14: =COUNTIFS(Checklist!$N$2:$N$89,8,Checklist!$J$2:$J$89,"Not applicable") -> 0 | H14: =COUNTIFS(Checklist!$N$2:$N$89,8,Checklist!$J$2:$J$89,"Not assessed") -> 46 | I14: =IF((C14-G14-H14)=0,"n/a",D14/(C14-G14-H14)) -> n/a
B15: 9 Performance evaluation | C15: =COUNTIF(Checklist!$N$2:$N$89,9) -> 7 | D15: =COUNTIFS(Checklist!$N$2:$N$89,9,Checklist!$J$2:$J$89,"Conforming") -> 0 | E15: =COUNTIFS(Checklist!$N$2:$N$89,9,Checklist!$J$2:$J$89,"Minor gap") -> 0 | F15: =COUNTIFS(Checklist!$N$2:$N$89,9,Checklist!$J$2:$J$89,"Major gap") -> 0 | G15: =COUNTIFS(Checklist!$N$2:$N$89,9,Checklist!$J$2:$J$89,"Not applicable") -> 0 | H15: =COUNTIFS(Checklist!$N$2:$N$89,9,Checklist!$J$2:$J$89,"Not assessed") -> 7 | I15: =IF((C15-G15-H15)=0,"n/a",D15/(C15-G15-H15)) -> n/a
B16: 10 Improvement | C16: =COUNTIF(Checklist!$N$2:$N$89,10) -> 5 | D16: =COUNTIFS(Checklist!$N$2:$N$89,10,Checklist!$J$2:$J$89,"Conforming") -> 0 | E16: =COUNTIFS(Checklist!$N$2:$N$89,10,Checklist!$J$2:$J$89,"Minor gap") -> 0 | F16: =COUNTIFS(Checklist!$N$2:$N$89,10,Checklist!$J$2:$J$89,"Major gap") -> 0 | G16: =COUNTIFS(Checklist!$N$2:$N$89,10,Checklist!$J$2:$J$89,"Not applicable") -> 0 | H16: =COUNTIFS(Checklist!$N$2:$N$89,10,Checklist!$J$2:$J$89,"Not assessed") -> 5 | I16: =IF((C16-G16-H16)=0,"n/a",D16/(C16-G16-H16)) -> n/a
B17: TOTAL | C17: =SUM(C10:C16) -> 88 | D17: =SUM(D10:D16) -> 0 | E17: =SUM(E10:E16) -> 0 | F17: =SUM(F10:F16) -> 0 | G17: =SUM(G10:G16) -> 0 | H17: =SUM(H10:H16) -> 88 | I17: =IF((C17-G17-H17)=0,"n/a",D17/(C17-G17-H17)) -> n/a
B19: Assessed % | C19: =IF(C17=0,0,(C17-H17)/C17) -> 0
B20: Open gaps (minor + major) | C20: =E17+F17 -> 0
B21: Open major gaps | C21: =F17 -> 0
B23: Results by requirement source
B24: Source | C24: Items | D24: Conforming | E24: Minor gap | F24: Major gap | G24: Not applicable | H24: Not assessed | I24: Conformity %
B25: ISO 9001 base | C25: =COUNTIF(Checklist!$C$2:$C$89,"ISO 9001 base") -> 38 | D25: =COUNTIFS(Checklist!$C$2:$C$89,"ISO 9001 base",Checklist!$J$2:$J$89,"Conforming") -> 0 | E25: =COUNTIFS(Checklist!$C$2:$C$89,"ISO 9001 base",Checklist!$J$2:$J$89,"Minor gap") -> 0 | F25: =COUNTIFS(Checklist!$C$2:$C$89,"ISO 9001 base",Checklist!$J$2:$J$89,"Major gap") -> 0 | G25: =COUNTIFS(Checklist!$C$2:$C$89,"ISO 9001 base",Checklist!$J$2:$J$89,"Not applicable") -> 0 | H25: =COUNTIFS(Checklist!$C$2:$C$89,"ISO 9001 base",Checklist!$J$2:$J$89,"Not assessed") -> 38 | I25: =IF((C25-G25-H25)=0,"n/a",D25/(C25-G25-H25)) -> n/a
B26: AS9100D addition | C26: =COUNTIF(Checklist!$C$2:$C$89,"AS9100D addition") -> 21 | D26: =COUNTIFS(Checklist!$C$2:$C$89,"AS9100D addition",Checklist!$J$2:$J$89,"Conforming") -> 0 | E26: =COUNTIFS(Checklist!$C$2:$C$89,"AS9100D addition",Checklist!$J$2:$J$89,"Minor gap") -> 0 | F26: =COUNTIFS(Checklist!$C$2:$C$89,"AS9100D addition",Checklist!$J$2:$J$89,"Major gap") -> 0 | G26: =COUNTIFS(Checklist!$C$2:$C$89,"AS9100D addition",Checklist!$J$2:$J$89,"Not applicable") -> 0 | H26: =COUNTIFS(Checklist!$C$2:$C$89,"AS9100D addition",Checklist!$J$2:$J$89,"Not assessed") -> 21 | I26: =IF((C26-G26-H26)=0,"n/a",D26/(C26-G26-H26)) -> n/a
B27: Mixed | C27: =COUNTIF(Checklist!$C$2:$C$89,"Mixed") -> 29 | D27: =COUNTIFS(Checklist!$C$2:$C$89,"Mixed",Checklist!$J$2:$J$89,"Conforming") -> 0 | E27: =COUNTIFS(Checklist!$C$2:$C$89,"Mixed",Checklist!$J$2:$J$89,"Minor gap") -> 0 | F27: =COUNTIFS(Checklist!$C$2:$C$89,"Mixed",Checklist!$J$2:$J$89,"Major gap") -> 0 | G27: =COUNTIFS(Checklist!$C$2:$C$89,"Mixed",Checklist!$J$2:$J$89,"Not applicable") -> 0 | H27: =COUNTIFS(Checklist!$C$2:$C$89,"Mixed",Checklist!$J$2:$J$89,"Not assessed") -> 29 | I27: =IF((C27-G27-H27)=0,"n/a",D27/(C27-G27-H27)) -> n/a
B29: Note | C29: Conformity % = Conforming ÷ (Items − Not applicable − Not assessed). Items with no status yet are excluded until assessed, so read Assessed % first. A low result in the AS9100D addition rows with a good ISO 9001 base result points to aerospace-specific controls (risk, configuration, product safety, counterfeit parts, special processes, first article inspection) as the first place to act. Indicative readiness measure only; not a certification outcome.
B31: © 2026 Cristian La Bella Consulting. All rights reserved. | cristianlabella.com

Sheet Checklist
A1: Clause | B1: Title | C1: Source | D1: Requirement (paraphrased) | E1: Audit question | F1: Objective evidence to request | G1: Common findings | H1: Follow-up questions | I1: Related IAQG docs | J1: Status | K1: Evidence seen / notes | L1: Owner | M1: Target date | N1: Main clause
A2: 4.1 | B2: Context of the organization | C2: ISO 9001 base | D2: Identify the external and internal issues relevant to purpose and strategic direction that affect the QMS results, and keep monitoring them. | E2: How does the organization identify and review the issues that affect its ability to deliver conforming, safe and on-time product to aerospace and defense customers? | F2: Context analysis (SWOT, PESTLE or similar), business plan, customer and market intelligence, management review inputs. | G2: Analysis prepared once for certification and never updated; ignores supply-chain, workforce, obsolescence or export-control issues that clearly affect delivery. | H2: Which issue changed in the last year, and what did the organization change in the QMS because of it? | J2: Not assessed | N2: =VALUE(LEFT(A2,FIND(".",A2)-1)) -> 4
A3: 4.2 | B3: Interested parties and their requirements | C3: ISO 9001 base | D3: Determine the interested parties relevant to the QMS and their relevant requirements, and monitor that information. | E3: Which interested parties (customers, regulators, certification body, primes, sub-tier providers) are relevant, and which of their requirements become QMS requirements? | F3: Interested-party register with requirements, customer quality clauses and contract flow-downs, regulatory and authority requirements list. | G3: Register names parties but not their requirements; customer-specific quality clauses sit with sales and are unknown to production; regulator or certification body missing. | H3: How does a new customer quality clause reach the process owner who has to implement it? | J3: Not assessed | N3: =VALUE(LEFT(A3,FIND(".",A3)-1)) -> 4
A4: 4.3 | B4: Scope of the QMS | C4: ISO 9001 base | D4: Define the boundaries and applicability of the QMS and keep the scope documented, with a justification for every requirement judged not applicable. Conformity can be claimed only if the exclusions do not affect product conformity or customer satisfaction. | E4: What is the QMS scope, and is any requirement declared not applicable (for example design, post-delivery activities, special processes)? Is each justification valid? | F4: Scope statement, site and product list, justification for each non-applicable requirement, contracts and drawings showing who holds design responsibility. | G4: Design excluded although the organization changes or approves drawings or process specifications; post-delivery excluded although it handles returns or repairs; a site or outsourced special process is missing from the scope. | H4: Who holds design authority for the parts in the scope, and where is that written down? | J4: Not assessed | N4: =VALUE(LEFT(A4,FIND(".",A4)-1)) -> 4
A5: 4.4.1 | B5: QMS and its processes (incl. customer and regulatory QMS requirements) | C5: Mixed | D5: Establish, implement, maintain and improve the QMS and its processes, with inputs, outputs, sequence, interaction, criteria, resources, owners and risks. The QMS must also address customer and applicable statutory and regulatory QMS requirements. | E5: Can you show the process map, the owner and measures of each process, and where customer and regulatory QMS requirements are built in? | F5: Process map or turtle diagrams, process owners, KPIs with targets and trends, matrix linking customer and regulatory requirements to processes. | G5: Processes drawn but no measurable output or named owner; customer requirements not mapped to any process; interfaces such as engineering to production left undefined. | H5: Pick a KPI that missed target. What did the process owner do, and when? | I5: 9101 | J5: Not assessed | N5: =VALUE(LEFT(A5,FIND(".",A5)-1)) -> 4
A6: 4.4.2 | B6: Documented information on QMS processes | C6: Mixed | D6: Maintain documented information to support the processes and retain records showing they run as planned. The documented description must cover relevant interested parties, scope, processes, their sequence and interaction, and responsibilities. | E6: Where is the documented description of the QMS (quality manual or equivalent), and does it match how the organization actually works? | F6: Quality manual or equivalent, process descriptions, records showing recent execution of each process. | G6: Manual copied from the standard; process descriptions out of date; record retention differs from site to site. | H6: Walk one process from its description to the record of its last execution. | I6: 9101 | J6: Not assessed | N6: =VALUE(LEFT(A6,FIND(".",A6)-1)) -> 4
A7: 5.1.1 | B7: Leadership and commitment | C7: ISO 9001 base | D7: Top management takes accountability for QMS effectiveness, aligns policy and objectives with direction, integrates the QMS into the business, promotes process approach and risk-based thinking, provides resources and supports other managers. | E7: How does top management show that it owns the QMS beyond signing the policy? | F7: Management review minutes, resourcing decisions, objectives reviews, staff communications, interview with top management. | G7: Quality delegated entirely to the quality manager; top management cannot describe objectives or delivery and quality performance; requests for calibration, training or inspection resources stalled. | H7: Which decision in the last 12 months was driven by QMS data? | J7: Not assessed | N7: =VALUE(LEFT(A7,FIND(".",A7)-1)) -> 5
A8: 5.1.2 | B8: Customer focus (conformity and on-time delivery) | C8: Mixed | D8: Ensure customer, statutory and regulatory requirements are determined and met, risks to conformity and satisfaction are addressed, and product conformity and on-time delivery are measured with action taken when results are or will be missed. | E8: How does top management see conformity and on-time delivery performance, and what happens when a delivery is forecast to be late? | F8: On-time delivery and quality dashboards, customer scorecards, recovery plans, management review records. | G8: On-time delivery measured against internal dates, not customer-confirmed dates; no action triggered by a forecast miss; customer scorecards never reviewed by management. | H8: Show a late delivery from last quarter, its recovery plan and what changed afterwards. | J8: Not assessed | N8: =VALUE(LEFT(A8,FIND(".",A8)-1)) -> 5
A9: 5.2.1-5.2.2 | B9: Quality policy | C9: ISO 9001 base | D9: Establish, maintain, communicate and make available a quality policy that fits purpose and context, commits to satisfy requirements and to continual improvement, and provides a framework for objectives. | E9: Is the policy appropriate, communicated, understood and available to interested parties? | F9: Current signed policy, display locations, induction material, staff interview answers. | G9: Policy generic or outdated; staff cannot say what it means for their job; no link to objectives. | H9: Ask three employees from different areas what the policy means for their work. | J9: Not assessed | N9: =VALUE(LEFT(A9,FIND(".",A9)-1)) -> 5
A10: 5.3 a | B10: Roles, responsibilities and authorities | C10: ISO 9001 base | D10: Assign, communicate and make understood the responsibilities and authorities for QMS roles, including conformity of the QMS, process outputs, performance reporting, customer focus and QMS integrity during change. | E10: How are QMS responsibilities and authorities assigned and communicated? | F10: Organization chart, job descriptions, authority matrix, appointment letters, evidence of communication. | G10: Organization chart outdated; nobody clearly authorized to stop nonconforming work or report QMS performance; authorities differ between documents. | H10: Who can stop a shipment, and where is that authority written? | J10: Not assessed | N10: =VALUE(LEFT(A10,FIND(".",A10)-1)) -> 5
A11: 5.3 b | B11: Management representative | C11: AS9100D addition | D11: Top management must appoint a specific member of management as management representative, with responsibility and authority to oversee the 5.3 responsibilities and free, unrestricted access to top management. | E11: Who is the management representative, how were they appointed, and can they reach top management without restriction? | F11: Appointment letter, organization chart, job description, evidence of direct access to top management. | G11: Role assigned in name only, or held by someone with no authority over production or purchasing; role vacant after a reorganization. | H11: Show an issue the representative escalated to top management and the outcome. | J11: Not assessed | N11: =VALUE(LEFT(A11,FIND(".",A11)-1)) -> 5
A12: 6.1.1 | B12: Risks and opportunities: determination | C12: ISO 9001 base | D12: When planning the QMS, consider context and interested parties and determine the risks and opportunities that must be addressed to give assurance of results, enhance desirable effects, prevent undesired effects and improve. | E12: How were QMS-level risks and opportunities determined, and how do they link to the operational risk process in 8.1.1? | F12: Risk and opportunity register, strategic plan, management review inputs, link to the operational risk process. | G12: One list made for the audit and never reviewed; QMS risks and operational risks managed in unrelated systems; opportunities ignored. | H12: Show a risk that materialized in the last year. Was it on the register beforehand? | J12: Not assessed | N12: =VALUE(LEFT(A12,FIND(".",A12)-1)) -> 6
A13: 6.1.2 | B13: Risks and opportunities: actions and effectiveness | C13: ISO 9001 base | D13: Plan actions to address the risks and opportunities, integrate them into QMS processes, and evaluate effectiveness. Actions must be proportionate to the potential impact on conformity of products and services. | E13: How are the resulting actions tracked, and how is their effectiveness judged? | F13: Action plans with owners and dates, effectiveness reviews, evidence of integration into process documents. | G13: Actions without owners or dates; effectiveness never checked; actions out of proportion to the impact on product conformity. | H13: Choose one closed action and show the evidence that it worked. | J13: Not assessed | N13: =VALUE(LEFT(A13,FIND(".",A13)-1)) -> 6
A14: 6.2.1 | B14: Quality objectives | C14: ISO 9001 base | D14: Set measurable quality objectives at relevant functions, levels and processes that are consistent with the policy, relevant to product conformity and customer satisfaction, monitored, communicated and updated. | E14: What are the quality objectives, who owns each, and how are they monitored? | F14: Objectives with targets, owners and measurement methods, monitoring records, communication evidence. | G14: Objectives not measurable or not tracked; the same objectives copied year after year; owners unaware of them. | H14: What happened the last time an objective was missed? | J14: Not assessed | N14: =VALUE(LEFT(A14,FIND(".",A14)-1)) -> 6
A15: 6.2.2 | B15: Planning to achieve objectives | C15: ISO 9001 base | D15: For each objective, determine what will be done, the resources, who is responsible, when it will be finished and how results will be evaluated. | E15: Where is the plan to achieve each objective, and how is progress reviewed? | F15: Objective action plans, resource allocations, progress reviews, management review records. | G15: Objectives set but no plan, owner or date behind them; progress reviewed only at management review. | H15: Show a plan from last year and its evaluated result. | J15: Not assessed | N15: =VALUE(LEFT(A15,FIND(".",A15)-1)) -> 6
A16: 6.3 | B16: Planning of changes | C16: ISO 9001 base | D16: Carry out QMS changes in a planned way, considering purpose and consequences, QMS integrity, resource availability and the allocation of responsibilities. | E16: How are QMS changes (new process, site, system, organization) planned and controlled? | F16: Change records, impact assessments, communication records, post-change reviews. | G16: Changes made informally; no assessment of impact on QMS integrity or on aerospace-specific controls such as traceability and configuration. | H16: Show the last significant change and how its impact was evaluated. | J16: Not assessed | N16: =VALUE(LEFT(A16,FIND(".",A16)-1)) -> 6
A17: 7.1.1 | B17: Resources: general | C17: ISO 9001 base | D17: Determine and provide the resources needed for the QMS, considering what internal resources can and cannot do and what must come from external providers. | E17: How does the organization decide what resources it needs and what must be sourced externally? | F17: Resource plans, budgets, capacity studies, management review resource decisions. | G17: Resource needs raised repeatedly with no decision recorded; capacity not compared with the order book. | H17: Show a resource request from the last year and what happened to it. | J17: Not assessed | N17: =VALUE(LEFT(A17,FIND(".",A17)-1)) -> 7
A18: 7.1.2 | B18: People | C18: ISO 9001 base | D18: Determine and provide the people needed to operate the QMS and control its processes. | E18: Does staffing match the workload in production, inspection, quality and purchasing? | F18: Headcount versus workload, overtime records, vacancy list, backlog of inspection or quality tasks. | G18: Single inspector for several shifts; chronic overtime in inspection; quality tasks skipped when the schedule is tight. | H18: Which role is the bottleneck when a delivery is at risk? | J18: Not assessed | N18: =VALUE(LEFT(A18,FIND(".",A18)-1)) -> 7
... A33: 8.1 b-e | B33: Process and acceptance criteria, resources, control and records | C33: Mixed | D33: Set criteria for processes and for acceptance, determine resources needed for conformity and for on-time delivery, apply control in line with the criteria, and keep documented information to show processes ran as planned and product conforms. | E33: How are process and acceptance criteria defined, and are resources planned against delivery dates? | F33: Process control plans, acceptance criteria, capacity and resource plans, statistical technique usage, records of process execution. | G33: Acceptance criteria not defined for new operations; capacity planning ignores inspection and special process lead times; statistical techniques used without recognized basis. | H33: For one process, show the criteria, the resources and the last record that it ran as planned. | J33: Not assessed | N33: =VALUE(LEFT(A33,FIND(".",A33)-1)) -> 8
A34: 8.1 f | B34: Critical items and key characteristics | C34: AS9100D addition | D34: Determine the processes and controls needed to manage critical items, including production controls where key characteristics are identified. | E34: Which items are designated critical or key characteristics for this product, and how are they controlled through production? | F34: Critical item and key characteristic lists, control plans, capability data, customer designations, work instructions flagging them. | G34: Key characteristics identified on drawings but not carried into travelers or inspection plans; no variation control or capability data; operators unaware of which features are critical. | H34: Pick a key characteristic and show its control from drawing to shipping record. | I34: 9103 | J34: Not assessed | N34: =VALUE(LEFT(A34,FIND(".",A34)-1)) -> 8
A35: 8.1 g-j | B35: Cross-functional planning, support, external providers, preventing delivery of nonconformity | C35: Mixed | D35: Engage affected functions in planning, determine support and maintenance of products and services, determine what is sourced externally, and put in place the controls needed to prevent delivery of nonconforming product or service. | E35: Who takes part in operational planning, and what stops a nonconforming product from reaching the customer? | F35: Planning meeting records with function sign-off, post-delivery support plans, outsourcing decisions, release gates and hold controls. | G35: Planning done by one department; release gates bypassed under schedule pressure; no documented controls beyond final inspection. | H35: Show a case where a release gate stopped a shipment. | J35: Not assessed | N35: =VALUE(LEFT(A35,FIND(".",A35)-1)) -> 8
A36: 8.1 project | B36: Project, program or contract planning | C36: AS9100D addition | D36: Where appropriate, plan and manage product and service provision in a structured, controlled way, with scheduled events in a planned sequence that meets requirements at acceptable risk within resource and schedule constraints. Planning output must suit the organization's operations. | E36: How are larger contracts and programs planned and tracked, and is there a quality plan for them? | F36: Project or program plans, quality plans, milestone and risk reviews, customer reporting. | G36: Large orders run on the master schedule with no program plan; risks not reviewed after kickoff; quality plan missing although customer asked for one. | H36: Show the plan for the most complex current contract and its last milestone review. | J36: Not assessed | N36: =VALUE(LEFT(A36,FIND(".",A36)-1)) -> 8
A37: 8.1 changes | B37: Planned and unintended changes, outsourced processes | C37: ISO 9001 base | D37: Control planned changes, review the consequences of unintended changes and act to reduce harm, and make sure outsourced processes stay under QMS control. | E37: How are unplanned changes (equipment failure, staff change, material substitution) detected and assessed? | F37: Change records, deviation records, impact reviews, outsourced process control records. | G37: Unplanned changes absorbed without assessment; outsourced processes controlled only by purchase order. | H37: Show a change nobody planned and how its effect on product was assessed. | J37: Not assessed | N37: =VALUE(LEFT(A37,FIND(".",A37)-1)) -> 8
A38: 8.1 transfer | B38: Work transfer | C38: AS9100D addition | D38: Establish a process to plan and control temporary or permanent transfer of work, ensuring continued conformity and managing the impacts and risks of the transfer. | E38: Has any work moved between sites, to a new external provider or back in-house, and how was the transfer controlled? | F38: Transfer plans, risk assessments, first article or revalidation records, customer approvals, training records at the receiving site. | G38: Work moved to a new provider with no risk assessment or first article; customer not told; knowledge not transferred. | H38: Show the last transfer, its risk assessment and how conformity was confirmed afterwards. | J38: Not assessed | N38: =VALUE(LEFT(A38,FIND(".",A38)-1)) -> 8
A39: 8.1.1 | B39: Operational risk management | C39: AS9100D addition | D39: Plan, implement and control a process to manage risks to meeting applicable requirements in operations: assign responsibility, define assessment criteria, identify, assess and communicate risks, act on risks above the acceptance limit, and formally accept residual risk. | E39: What is the operational risk process, which criteria does it use, and who accepts residual risk? | F39: Risk management procedure, criteria (likelihood, severity, acceptance), risk registers by program or process, FMEA or equivalent, records of risk acceptance. | G39: Process exists on paper but no registers in use; criteria undefined; residual risk accepted by nobody; risks not updated after nonconformities. | H39: Pick a high-risk requirement and show its risk, mitigation and acceptance record. | J39: Not assessed | N39: =VALUE(LEFT(A39,FIND(".",A39)-1)) -> 8
A40: 8.1.2 | B40: Configuration management | C40: AS9100D addition | D40: Plan, implement and control a configuration management process that controls physical and functional attributes through the product life cycle: product identity and traceability to requirements including approved changes, and consistency between documentation and the actual product. | E40: How does the organization make sure the product built matches the approved configuration, and how are changes controlled? | F40: Configuration management plan, baselines and revision control, change records, as-built records, configuration audits. | G40: Drawings and work instructions at different revisions; changes implemented without updating all documents; no check that as-built matches approved design. | H40: Take a delivered serial number and show its as-built configuration against the baseline. | J40: Not assessed | N40: =VALUE(LEFT(A40,FIND(".",A40)-1)) -> 8
A41: 8.1.3 | B41: Product safety | C41: AS9100D addition | D41: Plan, implement and control the processes needed to ensure product safety across the whole product life cycle, as appropriate to the organization and the product, for example hazard assessment, management of safety critical items, event analysis and reporting, and training. | E41: How does the organization control product safety, and what happens when an event could affect safety? | F41: Product safety procedure, hazard assessments, safety critical item list, event reports, safety training records. | G41: Product safety treated as general quality; no safety critical item list; events affecting safety not escalated or reported to customers. | H41: Show a recent event with possible safety impact and how it was handled and communicated. | J41: Not assessed | N41: =VALUE(LEFT(A41,FIND(".",A41)-1)) -> 8
A42: 8.1.4 | B42: Prevention of counterfeit parts | C42: AS9100D addition | D42: Plan, implement and control processes appropriate to the organization and product to prevent use of counterfeit or suspect counterfeit parts and their inclusion in delivered product. Typical elements: awareness training, obsolescence monitoring, approved sources, traceability to the original manufacturer, detection tests, monitoring of alerts, quarantine and reporting. | E42: How does the organization prevent counterfeit parts from entering the product, and what happens when one is suspected? | F42: Counterfeit prevention procedure, approved source lists, purchasing controls, training records, test or inspection methods, alert monitoring, quarantine records. | G42: Procedure exists but buyers untrained; purchases from brokers with no extra verification; suspect part handling not defined; no alert monitoring. | H42: Show how the last purchase from a non-franchised source was assessed and verified. | J42: Not assessed | N42: =VALUE(LEFT(A42,FIND(".",A42)-1)) -> 8
A43: 8.2.1 | B43: Customer communication | C43: Mixed | D43: Communicate with customers on product information, enquiries, contracts and orders (including changes), feedback and complaints, customer property, and establish specific contingency requirements where relevant. | E43: How does the organization communicate with customers, and is there a defined contingency approach where the customer requires one? | F43: Customer communication records, order change notices, complaint records, contingency plans, customer property records. | G43: No contingency arrangements even where customer requires them; order changes accepted by phone without record; complaints tracked by sales only. | H43: Show a customer contingency requirement and the plan that answers it. | J43: Not assessed | N43: =VALUE(LEFT(A43,FIND(".",A43)-1)) -> 8
A44: 8.2.2 | B44: Determining requirements (special requirements and operational risks) | C44: Mixed | D44: Define product and service requirements including statutory and regulatory ones, confirm the organization can meet its claims, determine special requirements, and identify operational risks such as new technology, capacity or short lead time. | E44: How are special requirements identified at quotation and order stage, and how are they passed on? | F44: Quotation and order review records, special requirement lists, risk notes, feasibility assessments. | G44: Special requirements recognized only after production starts; operational risks not recorded at review; regulatory requirements not checked. | H44: Take a recent order and show the special requirements found and who received them. | J44: Not assessed | N44: =VALUE(LEFT(A44,FIND(".",A44)-1)) -> 8
A45: 8.2.3 | B45: Review of requirements | C45: ISO 9001 base | D45: Before committing to supply, review customer requirements, unstated requirements needed for use, the organization's own requirements, regulatory requirements and differences from earlier requirements, and retain the results. | E45: What is checked before the organization accepts an order or contract, and are differences from the quote resolved? | F45: Contract review records, sign-offs from affected functions, resolved differences, confirmation of verbal orders. | G45: Orders accepted automatically with no review; differences between order and quote unresolved; review not coordinated with engineering or production. | H45: Select two orders and show who reviewed each and what was resolved. | J45: Not assessed | N45: =VALUE(LEFT(A45,FIND(".",A45)-1)) -> 8
A46: 8.2.4 | B46: Changes to requirements | C46: ISO 9001 base | D46: When requirements change, amend documented information and make relevant people aware. | E46: How do changes to customer requirements reach everyone who needs them? | F46: Change notices, amended orders, distribution evidence, work instruction updates. | G46: Changes to purchase orders not reflected on travelers; operators working to old requirements. | H46: Follow one change from the order to the shop floor document. | J46: Not assessed | N46: =VALUE(LEFT(A46,FIND(".",A46)-1)) -> 8
... A50: 8.3.4.1 | B50: Testing for verification and validation | C50: AS9100D addition | D50: Plan, control, review and document tests used for verification and validation: test plans identify item, resources, objectives, conditions, parameters and criteria; procedures define methods and records; correct test item configuration; compliance with plans; acceptance criteria met. Test equipment is controlled under 7.1.5. Conclude with reports proving the design meets requirements across operating conditions. | E50: How do you show that tests were carried out on the correct configuration with controlled equipment against defined criteria? | F50: Test plans and procedures, configuration records of test items, calibrated test equipment records, test reports. | G50: Test item configuration not recorded; test equipment out of calibration; acceptance criteria defined after testing; reports do not cover all operating conditions. | H50: Select a test report and show its plan, test item configuration and equipment calibration. | J50: Not assessed | N50: =VALUE(LEFT(A50,FIND(".",A50)-1)) -> 8
A51: 8.3.5 | B51: Design and development outputs (critical items and data) | C51: Mixed | D51: Outputs must meet inputs, support later processes, include acceptance criteria, specify characteristics essential to safe and proper use, identify critical items and key characteristics with actions, and be approved before release. Define the data needed to identify, make, verify, use and maintain the product, and retain records. | E51: Do design outputs identify critical items and key characteristics and give production and inspection what they need? | F51: Released drawings and models, parts lists, specifications, critical item and key characteristic designations, approval records. | G51: Critical items not flagged on released data; incomplete data package; release without authorized approval. | H51: Show a released drawing and its critical item identification and approval. | I51: 9103 | J51: Not assessed | N51: =VALUE(LEFT(A51,FIND(".",A51)-1)) -> 8
A52: 8.3.6 | B52: Design and development changes | C52: Mixed | D52: Identify, review and control design changes so there is no adverse effect on conformity. Have a process with criteria for notifying the customer before implementing changes that affect customer requirements. Retain records of changes, reviews, authorization and actions. Control design changes under configuration management. | E52: How do you decide whether a design change needs customer notification, and how is it tied into configuration control? | F52: Change records, customer notification criteria and records, review and authorization evidence, configuration updates. | G52: No criteria for customer notification; changes implemented before approval; configuration records not updated. | H52: Show a recent change that required customer approval and when it was obtained. | I52: 9116 | J52: Not assessed | N52: =VALUE(LEFT(A52,FIND(".",A52)-1)) -> 8
A53: 8.4.1 a | B53: External providers: responsibility, customer-designated sources and risk | C53: Mixed | D53: The organization is responsible for conformity of everything externally provided, including from customer-defined sources. Use customer-designated or approved providers when required, identify and manage risks of external provision and provider selection, and require providers to apply appropriate controls to their own sub-tier providers. | E53: How does the organization remain responsible for externally provided product, and how does it manage customer-designated sources and sub-tier risk? | F53: Purchasing procedure, customer-designated source list, risk assessments of providers, flow-down evidence to sub-tier providers. | G53: Customer-designated sources used without checking current approval; no risk assessment of providers; sub-tier controls not required. | H53: Show the sub-tier controls required of a critical provider. | I53: 9134 | J53: Not assessed | N53: =VALUE(LEFT(A53,FIND(".",A53)-1)) -> 8
A54: 8.4.1 b | B54: Evaluation, selection, monitoring and re-evaluation of providers | C54: ISO 9001 base | D54: Apply criteria for evaluating, selecting, monitoring and re-evaluating external providers based on their ability to supply to requirements, and retain records. Third-party quality data may be used but the organization stays responsible for verifying conformity. | E54: How are providers selected and re-evaluated, and what data is used? | F54: Evaluation and selection records, scorecards, audit reports, certification status checks, re-evaluation records. | G54: Provider approved on certificate alone; scorecards not updated; re-evaluation never carried out. | H54: Show the evaluation file of one critical provider and its last re-evaluation. | I54: 9134 | J54: Not assessed | N54: =VALUE(LEFT(A54,FIND(".",A54)-1)) -> 8
A55: 8.4.1.1 | B55: Provider approval status and register | C55: AS9100D addition | D55: Define the process, responsibility and authority for approving providers, changing approval status and the conditions for controlled use; keep a register showing approval status and scope; review provider performance periodically; define actions for providers that miss requirements; and set controls for documented information held by providers. | E55: Is there a register with approval status and scope for every provider, and does purchasing respect it? | F55: Approved provider register with status and scope, status change records, performance reviews, corrective action requests to providers. | G55: Register lacks scope of approval; orders placed with disapproved or conditional providers; on-time delivery and conformity not reviewed together; no defined action for poor performers. | H55: Pick three purchase orders and match each to the provider's status and approved scope. | J55: Not assessed | N55: =VALUE(LEFT(A55,FIND(".",A55)-1)) -> 8
A56: 8.4.2 a-c | B56: Type and extent of control | C56: ISO 9001 base | D56: Ensure externally provided processes, products and services do not adversely affect the ability to deliver conforming product: keep outsourced processes within QMS control, define controls for the provider and for the output, and consider impact, provider control effectiveness and performance reviews. | E56: How does the organization decide the type and extent of control for each provider and product? | F56: Control level definitions, risk-based control plans, receiving inspection plans, provider performance reviews. | G56: Same controls applied to every provider regardless of risk; control level not reviewed after nonconformities. | H56: Show how control changed after a provider nonconformity. | J56: Not assessed | N56: =VALUE(LEFT(A56,FIND(".",A56)-1)) -> 8
A57: 8.4.2 verification | B57: Verification of external product, release pending verification | C57: AS9100D addition | D57: Verification must reflect the identified risks and include inspection or periodic testing where nonconformity risk is high, including counterfeit parts. If product is released for production before verification is complete, it must be identified and recorded to allow recall and replacement. | E57: Is verification of purchased product based on risk, and is product released pending verification traceable? | F57: Receiving inspection plans with risk basis, test records, positive recall records, release-pending-verification records. | G57: Verification identical for all products; no extra checks for counterfeit risk; product released early with no recall identification. | H57: Take a product released pending verification and show how it could be recalled. | I57: 9102, 9133 | J57: Not assessed | N57: =VALUE(LEFT(A57,FIND(".",A57)-1)) -> 8
A58: 8.4.2 delegation | B58: Delegated verification | C58: AS9100D addition | D58: When verification is delegated to an external provider, define the scope and requirements of delegation, keep a register of delegations and periodically monitor the provider's delegated verification. | E58: Which verification activities are delegated to providers, and how is delegation controlled and monitored? | F58: Delegation agreements, delegation register, monitoring or audit records of delegated activities. | G58: Delegation exists by habit with no agreement or register; no monitoring of delegated inspection; customers not informed where required. | H58: Show the register and the last check of a delegated activity. | J58: Not assessed | N58: =VALUE(LEFT(A58,FIND(".",A58)-1)) -> 8
A59: 8.4.2 test reports | B59: External test reports and raw material validation | C59: AS9100D addition | D59: When provider test reports verify purchased product, evaluate the data in the reports to confirm requirements are met. Where raw material is a significant operational risk, for example critical items, validate the accuracy of the test reports. | E59: Are provider test reports reviewed against requirements, and is accuracy validated for high-risk material? | F59: Test report review records, independent test results, validation sampling plans, material certificates. | G59: Certificates filed without review; no independent testing for critical raw material; discrepancies between certificate and specification not noticed. | H59: Select a critical material and show how its test report was verified. | J59: Not assessed | N59: =VALUE(LEFT(A59,FIND(".",A59)-1)) -> 8
A60: 8.4.3 a-j | B60: Information for external providers: technical and approval requirements | C60: Mixed | D60: Check the adequacy of requirements before sending them. Tell providers the requirements for the product or process including technical data, approvals, competence, interaction, performance monitoring, verification at their premises, design control, special requirements, critical items and key characteristics, tests and inspection, and statistical acceptance rules. | E60: What information do purchase orders carry, and who checks it before release? | F60: Purchase orders and attachments, technical data packages, review before release, records of agreed requirements. | G60: Purchase orders reference drawings without revision; key characteristics and special requirements not passed on; no review before release. | H60: Compare a purchase order with the customer order and drawing for completeness. | I60: 9103, 9116 | J60: Not assessed | N60: =VALUE(LEFT(A60,FIND(".",A60)-1)) -> 8
A61: 8.4.3 k-m | B61: Information for external providers: flow-down, access and awareness | C61: AS9100D addition | D61: Require providers to implement a QMS, use customer-designated sources, report nonconformities and obtain disposition approval, prevent counterfeit parts, notify changes including changes of sub-tier or manufacturing location, flow down requirements, provide test specimens, and retain records. Secure right of access for the organization, its customer and regulators at any supply-chain level, and ensure providers' staff know about conformity, product safety and ethics. | E61: How are these flow-down items placed in purchase orders and how do you know providers comply? | F61: Standard terms and conditions, flow-down matrix, provider acknowledgements, audit records, right-of-access clause. | G61: Terms and conditions missing counterfeit, change notification or right-of-access clauses; flow-downs not tailored to the customer contract; no evidence providers comply. | H61: Show the clauses in your standard order terms covering change notification and right of access. | I61: 9116 | J61: Not assessed | N61: =VALUE(LEFT(A61,FIND(".",A61)-1)) -> 8
A62: 8.5.1 a-c | B62: Controlled conditions: documented information, measurement and acceptance | C62: Mixed | D62: Run production under controlled conditions: documented product definition and activity instructions are available; suitable monitoring and measuring resources are used; verification is done at suitable stages. Acceptance documents must state criteria, where in the sequence verification happens, results retained (at least accept or reject) and the equipment needed. Sampling plans must rest on recognized statistical principles and match product criticality and process capability. | E62: At the workstation, what documents define the part and the activity, and where is acceptance recorded? | F62: Travelers, work instructions, drawings at current revision, inspection plans, sampling plans with justification, measurement records. | G62: Work instructions lack acceptance criteria or inspection point; sampling plan not justified for critical characteristics; only an overall pass recorded. | H62: Choose a job in progress and trace each requirement to its instruction and its record. | I62: 9103, 9162 | J62: Not assessed | N62: =VALUE(LEFT(A62,FIND(".",A62)-1)) -> 8
A63: 8.5.1 d-i | B63: Controlled conditions: infrastructure, competence, special processes, human error, workmanship | C63: Mixed | D63: Use suitable infrastructure and environment, appoint competent and where required qualified persons, validate and periodically revalidate processes whose output cannot be verified later, act to prevent human error, define release, delivery and post-delivery activities, and set workmanship criteria such as written standards or representative samples. | E63: What has the organization done to prevent human error, and how is workmanship defined? | F63: Error-proofing measures (poka-yoke, checklists), qualification records, workmanship standards and samples, process revalidation records. | G63: Human error analysed only after escapes; no workmanship standard for visual defects; operator qualification not linked to the task. | H63: Show an error-proofing measure introduced after a nonconformity and its effect. | I63: 9103, 9162 | J63: Not assessed | N63: =VALUE(LEFT(A63,FIND(".",A63)-1)) -> 8
A64: 8.5.1 j-n | B64: Controlled conditions: accountability, critical items, variable data and in-process verification | C64: Mixed | D64: Account for all products during production (quantities, split orders, nonconforming product), control and monitor critical items including key characteristics, set methods for measuring variable data, define in-process inspection points where later verification cannot confirm conformity, and keep evidence that all production and inspection operations were completed as planned or authorized. | E64: How do you account for every part in a lot, and how do you prove all planned operations were completed? | F64: Lot reconciliation records, split-order controls, key characteristic data and charts, in-process inspection records, operation completion sign-offs. | G64: Quantity reconciliation not done at splits; key characteristic data not trended; operations skipped without authorized deviation; stamps applied before work finished. | H64: Reconcile a closed lot from material issue to shipment. | I64: 9103, 9162 | J64: Not assessed | N64: =VALUE(LEFT(A64,FIND(".",A64)-1)) -> 8
A65: 8.5.1 o-q | B65: Controlled conditions: foreign objects, utilities and release pending verification | C65: AS9100D addition | D65: Provide for prevention, detection and removal of foreign objects, control and monitor utilities and supplies (water, compressed air, power, chemicals) to the extent they affect conformity, and identify and record product released for later production before all measurement is complete so it can be recalled. | E65: How are foreign objects prevented and detected, and how are utilities that affect product controlled? | F65: Foreign object prevention procedure, tool and consumable control, housekeeping audits, utility monitoring records, release-pending records. | G65: No tool control in assembly or machining areas; compressed air or coolant quality never monitored; products released early with no recall marking. | H65: Show the tool control method in a critical assembly or cleaning area. | I65: 9162 | J65: Not assessed | N65: =VALUE(LEFT(A65,FIND(".",A65)-1)) -> 8
A66: 8.5.1.1 | B66: Control of equipment, tools and software programs | C66: AS9100D addition | D66: Validate equipment, tools and software programs that automate, control, monitor or measure production before release for production, maintain them, and define storage requirements including periodic preservation or condition checks for stored equipment and tooling. | E66: How are tooling, fixtures and programs (including CNC and test programs) validated before use and controlled in storage? | F66: Program validation and first-run records, tool and fixture qualification, program revision control, storage condition checks. | G66: CNC programs changed at the machine without control; fixtures not verified; stored tooling never checked. | H66: Take a CNC program in use and show its validation and revision history. | J66: Not assessed | N66: =VALUE(LEFT(A66,FIND(".",A66)-1)) -> 8
A67: 8.5.1.2 | B67: Validation and control of special processes | C67: AS9100D addition | D67: For processes whose output cannot be verified by later monitoring or measurement, set arrangements covering process approval criteria, conditions to maintain approval, approval of facilities and equipment, qualification of people, specific methods and procedures, and records. | E67: Which special processes does the organization run or outsource (for example heat treatment, plating, welding, NDT) and how are they approved? | F67: Special process list, process approvals and customer or Nadcap approvals, personnel qualifications, equipment surveys, process records and test coupons. | G67: Special process list incomplete; approvals expired; operators qualified for a different process; process parameters not recorded. | H67: Take one special process and show approval, operator qualification and the last batch record. | J67: Not assessed | N67: =VALUE(LEFT(A67,FIND(".",A67)-1)) -> 8
A68: 8.5.1.3 | B68: Production process verification and first article inspection | C68: AS9100D addition | D68: Run activities that confirm the production process can make conforming product (risk assessments, capacity and capability studies, control plans). Use a representative item from the first production run of a new part or assembly to verify processes, documents and tooling, and repeat when changes invalidate earlier results. Retain results. This is generally called first article inspection (FAI). | E68: When is first article inspection performed and repeated, and what does it cover? | F68: FAI reports, triggers for repeat FAI (engineering, process, tooling, location changes), capability studies, control plans. | G68: FAI done on a prototype instead of a representative production item; not repeated after a tooling or process change; FAI report incomplete or characteristics missing. | H68: Select a part with an engineering change and show its repeat FAI. | I68: 9102 | J68: Not assessed | N68: =VALUE(LEFT(A68,FIND(".",A68)-1)) -> 8
A69: 8.5.2 | B69: Identification and traceability | C69: Mixed | D69: Identify outputs where necessary for conformity, keep the identification of configuration so differences from the required configuration can be seen, show monitoring and measurement status through production, control acceptance authority media (stamps, e-signatures, passwords), and keep records enabling traceability. | E69: Can you trace a delivered product back to material, process and inspection records, and forward from a material batch to its destinations? | F69: Traceability records, lot and serial controls, status labels, stamp and electronic signature controls, parts marking records. | G69: Traceability lost at splits or rework; stamps unsecured or shared; electronic signatures not controlled; configuration not identifiable on parts. | H69: Pick one serial number and trace it back to material and forward to shipment. | I69: 9132 | J69: Not assessed | N69: =VALUE(LEFT(A69,FIND(".",A69)-1)) -> 8
A70: 8.5.3 | B70: Property belonging to customers or external providers | C70: ISO 9001 base | D70: Take care of customer and provider property under the organization's control, identify, verify, protect and safeguard it, and report and record loss, damage or unsuitability. | E70: How is customer-supplied material, tooling and data identified and protected? | F70: Customer property register, storage controls, incoming checks, loss or damage reports to the customer. | G70: Customer tooling stored without identification; damage not reported; supplied data not controlled. | H70: Show the register and the last report to a customer about its property. | J70: Not assessed | N70: =VALUE(LEFT(A70,FIND(".",A70)-1)) -> 8
A71: 8.5.4 | B71: Preservation | C71: Mixed | D71: Preserve outputs to the extent needed for conformity. Where applicable, also provide for cleaning, foreign object control, special handling and storage for sensitive products, marking and labelling with safety warnings, shelf life control and stock rotation, and handling of hazardous materials. | E71: How are sensitive items, shelf-life materials and hazardous materials stored and rotated? | F71: Storage and handling procedures, shelf-life registers, FIFO or FEFO controls, packaging specifications, condition checks. | G71: Shelf-life items past expiry still in stock; no segregation of sensitive items; packaging does not follow customer specification. | H71: Walk the store and check three shelf-life items against the register. | J71: Not assessed | N71: =VALUE(LEFT(A71,FIND(".",A71)-1)) -> 8
A72: 8.5.5 | B72: Post-delivery activities | C72: Mixed | D72: Meet post-delivery requirements, considering statutory and regulatory requirements, undesired consequences, product life, customer requirements and feedback, in-service data, technical documentation, off-site work and product or customer support. Investigate and report problems found after delivery. | E72: What post-delivery obligations exist (warranty, repair support, technical data, in-service feedback), and how are problems handled? | F72: Warranty and support records, in-service data analysis, technical documentation updates, off-site work controls, investigation records. | G72: Post-delivery treated as out of scope although warranty or support exists; in-service feedback not analysed; no process for off-site work. | H72: Show how a problem reported after delivery was investigated and reported. | J72: Not assessed | N72: =VALUE(LEFT(A72,FIND(".",A72)-1)) -> 8
A73: 8.5.6 | B73: Control of changes in production or service provision | C73: Mixed | D73: Review and control changes to production or service provision, identify who may approve changes, and retain records of review results, authorization and actions. Changes can affect processes, equipment, tools or software programs. | E73: Who is authorized to approve process, equipment, tooling and program changes, and what is verified after each change? | F73: Process change requests, approval records, post-change verification and FAI records, customer notifications where required. | G73: Changes made by supervisors with no approval; no verification after change; customer not notified where contract requires it. | H73: Show a recent process change, who authorized it and what was verified. | I73: 9116 | J73: Not assessed | N73: =VALUE(LEFT(A73,FIND(".",A73)-1)) -> 8
A74: 8.6 | B74: Release of products and services | C74: Mixed | D74: Verify at planned stages that requirements are met and do not release until arrangements are satisfied, unless approved by a relevant authority and where applicable the customer. Retain evidence of conformity and traceability to the person authorizing release; where product qualification is required, evidence must show it. All required documentation must accompany delivery. | E74: What must be complete before shipment, and who authorizes release? | F74: Release records, certificates of conformity, inspection and test records, shipping documentation checklist, authorization lists. | G74: Release by people not authorized; documents missing at delivery; release with open actions and no concession approval. | H74: Take a shipment and verify each required document against the checklist. | I74: 9107, 9114, 9133, 9162 | J74: Not assessed | N74: =VALUE(LEFT(A74,FIND(".",A74)-1)) -> 8
A75: 8.7.1 a | B75: Nonconforming outputs: control process | C75: Mixed | D75: Identify and control nonconforming outputs, including product found after delivery or supplied by providers, take appropriate action, and maintain a documented process defining responsibility and authority for review and disposition, containment, timely customer notification and corrective action after delivery. | E75: How are nonconformities identified, contained and reported, and who can disposition them? | F75: Nonconformity procedure, nonconforming material reports, quarantine areas, disposition authority list, customer notification records. | G75: Quarantine areas not controlled; dispositions made by people without authority; customers not told of escaped nonconformities. | H75: Show a nonconformity found after delivery and the customer notification. | I75: 9131 | J75: Not assessed | N75: =VALUE(LEFT(A75,FIND(".",A75)-1)) -> 8
A76: 8.7.1 b | B76: Nonconforming outputs: disposition, scrap and counterfeit control | C76: AS9100D addition | D76: Use-as-is and repair dispositions need approval by design authority or delegated persons, and customer authorization when contract requirements are departed from. Scrap must be conspicuously and permanently marked or positively controlled until unusable. Counterfeit and suspect parts must be controlled to prevent re-entry into the supply chain. Verify conformity after correction. | E76: Who approves use-as-is and repair dispositions, and how is scrap controlled? | F76: Material review board records, design authority approvals, customer concession records, scrap marking and disposal records, reinspection records. | G76: Use-as-is approved by quality only; customer concession not requested where required; scrap bins open and unmarked; reworked parts not re-verified. | H76: Select a use-as-is disposition and show the design approval and customer authorization. | I76: 9131 | J76: Not assessed | N76: =VALUE(LEFT(A76,FIND(".",A76)-1)) -> 8
A77: 8.7.2 | B77: Nonconformity records | C77: ISO 9001 base | D77: Retain records describing the nonconformity, the actions taken, concessions obtained and the authority that decided the action. | E77: Do nonconformity records give enough information to understand what happened and what was decided? | F77: Nonconformity reports, concession records, disposition decisions with authority. | G77: Records vague or incomplete; no link to affected lots; decision authority not identified. | H77: Select two reports and reconstruct what happened from the record alone. | I77: 9131 | J77: Not assessed | N77: =VALUE(LEFT(A77,FIND(".",A77)-1)) -> 8
A78: 9.1.1 | B78: Monitoring and measurement: general | C78: ISO 9001 base | D78: Determine what to monitor and measure, the methods, the timing, and when results are analysed and evaluated; evaluate QMS performance and effectiveness and retain evidence. | E78: What does the organization measure to know the QMS works, and how often is it reviewed? | F78: Measurement plan, KPI reports, analysis records, evidence of use in decision making. | G78: Data collected but not analysed; KPIs measure activity, not results; no link to objectives. | H78: Pick a KPI and show a decision it informed. | J78: Not assessed | N78: =VALUE(LEFT(A78,FIND(".",A78)-1)) -> 9
A79: 9.1.2 | B79: Customer satisfaction (incl. delivery, complaints, corrective action requests) | C79: Mixed | D79: Monitor customer perception and determine the methods. The information must include product conformity, on-time delivery, complaints and corrective action requests. Develop and implement plans to improve customer satisfaction where deficiencies are found, and assess their effectiveness. | E79: How does the organization know customer perception and what plans exist where it is poor? | F79: Customer scorecards and feedback, complaint and corrective action request logs, satisfaction improvement plans, effectiveness reviews. | G79: Only surveys used; scorecards not analysed; no improvement plan after poor ratings; effectiveness not assessed. | H79: Show a customer rating drop and the plan that followed. | J79: Not assessed | N79: =VALUE(LEFT(A79,FIND(".",A79)-1)) -> 9
A80: 9.1.3 | B80: Analysis and evaluation of data | C80: ISO 9001 base | D80: Analyse and evaluate data to judge product conformity, customer satisfaction, QMS performance, planning effectiveness, effectiveness of risk and opportunity actions, provider performance and need for improvement. External sources such as industry alerts can be input. | E80: Where do trends from nonconformities, audits, deliveries and providers come together? | F80: Trend analyses, Pareto charts, data review records, alert monitoring. | G80: Analysis limited to counts; provider performance not included; external alerts ignored. | H80: Show a trend that led to a corrective or preventive action. | J80: Not assessed | N80: =VALUE(LEFT(A80,FIND(".",A80)-1)) -> 9
A81: 9.2.1-9.2.2 a-b | B81: Internal audit programme | C81: ISO 9001 base | D81: Audit at planned intervals to determine whether the QMS conforms to the organization's own requirements (including customer, statutory and regulatory ones), to the standard, and is effectively implemented and maintained. Plan a programme considering process importance, changes and earlier results, with defined criteria and scope for each audit. | E81: Is the audit programme risk-based and does it cover all processes, shifts and requirements including customer-specific ones? | F81: Audit programme, schedule, audit plans with criteria and scope, previous results used as input. | G81: Audits not scheduled by process importance; customer requirements never audited; shifts and sites missing; checklist only against the standard. | H81: Show how the last year's findings shaped this year's programme. | I81: 9101 | J81: Not assessed | N81: =VALUE(LEFT(A81,FIND(".",A81)-1)) -> 9
A82: 9.2.2 c-f | B82: Internal audit execution: objectivity, reporting and follow-up | C82: ISO 9001 base | D82: Select auditors to ensure objectivity and impartiality, report results to relevant management, take correction and corrective action without undue delay, and retain evidence of the programme and results. | E82: Are auditors independent of the area audited, and are findings closed on time? | F82: Auditor qualifications and independence evidence, audit reports, corrective action tracking, overdue action reports. | G82: Auditors audit their own area; findings open for months; reports not seen by management; auditor competence not shown. | H82: Pick a finding from the last audit and show its closure and verification. | I82: 9101 | J82: Not assessed | N82: =VALUE(LEFT(A82,FIND(".",A82)-1)) -> 9
A83: 9.3.1-9.3.2 | B83: Management review: planning and inputs (incl. delivery and provider performance) | C83: Mixed | D83: Review the QMS at planned intervals for suitability, adequacy, effectiveness and alignment with direction. Inputs include previous actions, changes in issues, performance trends (customer satisfaction, objectives, process and product conformity, nonconformities, monitoring results, audits, provider performance, on-time delivery), resource adequacy, effectiveness of risk actions and opportunities. | E83: Does management review cover all required inputs, especially on-time delivery and external provider performance? | F83: Management review agenda, minutes, input data packs, attendance records. | G83: Required inputs missing, especially delivery and provider performance; review is a presentation with no discussion; top management absent. | H83: Show the last review's input pack and who attended. | J83: Not assessed | N83: =VALUE(LEFT(A83,FIND(".",A83)-1)) -> 9
A84: 9.3.3 | B84: Management review: outputs | C84: ISO 9001 base | D84: Outputs must include decisions and actions on improvement opportunities, needed QMS changes, resource needs and risks identified, and records must be retained. | E84: What decisions and actions came out of the last management review, and are they tracked? | F84: Management review actions with owners and dates, resource approvals, follow-up in the next review. | G84: Minutes record discussion but no decisions; actions not tracked to closure; resource needs ignored. | H84: Show an action from the last review and its status. | J84: Not assessed | N84: =VALUE(LEFT(A84,FIND(".",A84)-1)) -> 9
A85: 10.1 | B85: Improvement: general | C85: ISO 9001 base | D85: Determine and select opportunities for improvement and act to meet customer requirements and enhance satisfaction: improve products and services, correct, prevent or reduce undesired effects, and improve QMS performance and effectiveness. | E85: How are improvement opportunities identified, prioritized and acted on? | F85: Improvement register, project records, results data. | G85: Improvement limited to corrective actions; no prioritization; results not measured. | H85: Show an improvement project and its measured result. | J85: Not assessed | N85: =VALUE(LEFT(A85,FIND(".",A85)-1)) -> 10
A86: 10.2.1 a-f | B86: Nonconformity and corrective action: reaction, root cause and effectiveness | C86: Mixed | D86: On a nonconformity, including a complaint, control and correct it and deal with consequences; evaluate the need to remove causes by reviewing and analysing it, determining causes including human factors, and checking for similar nonconformities; implement action, review its effectiveness, update risks and make QMS changes if necessary. | E86: Is root cause analysis thorough (including human factors) and is effectiveness checked? | F86: Corrective action reports (8D or equivalent), root cause analyses, effectiveness checks, risk register updates. | G86: Root cause given as operator error and closed with retraining; effectiveness not verified; similar nonconformities elsewhere not considered. | H86: Select a repeat nonconformity and show why the first corrective action did not work. | I86: 9131 | J86: Not assessed | N86: =VALUE(LEFT(A86,FIND(".",A86)-1)) -> 10
A87: 10.2.1 g-h | B87: Corrective action: provider flow-down and escalation | C87: AS9100D addition | D87: Flow down corrective action requirements to external providers when they are responsible for the nonconformity, and take specific action when timely, effective corrective action is not achieved. | E87: How are corrective actions passed to providers and what happens when they are late or ineffective? | F87: Supplier corrective action requests, response tracking, escalation records, provider status changes. | G87: Provider issues handled by email with no tracking; late responses not escalated; provider status not changed after repeat failures. | H87: Show a provider corrective action request that was escalated. | I87: 9131 | J87: Not assessed | N87: =VALUE(LEFT(A87,FIND(".",A87)-1)) -> 10
A88: 10.2.1-10.2.2 | B88: Corrective action process and records | C88: ISO 9001 base | D88: Maintain documented information defining the nonconformity and corrective action process, and retain records of the nature of nonconformities, actions taken and results of corrective action. Actions must be appropriate to the effects of the nonconformities. | E88: Is there a documented corrective action process and do records show nature, actions and results? | F88: Corrective action procedure, register, completed reports. | G88: Procedure and practice differ; records incomplete; actions out of proportion to effects. | H88: Pick three actions and show the full chain from nonconformity to result. | I88: 9131 | J88: Not assessed | N88: =VALUE(LEFT(A88,FIND(".",A88)-1)) -> 10
A89: 10.3 | B89: Continual improvement | C89: ISO 9001 base | D89: Continually improve suitability, adequacy and effectiveness of the QMS, considering analysis results and management review outputs, and monitor and evaluate the effectiveness of improvement actions. | E89: What evidence shows the QMS is improving over time? | F89: Trend data over several periods, improvement projects, lessons learned. | G89: Improvement claimed with no trend data; same issues recur each year. | H89: Show a metric that improved over two years and what caused it. | J89: Not assessed | N89: =VALUE(LEFT(A89,FIND(".",A89)-1)) -> 10

Sheet Aerospace Reference
B2: Aerospace Reference
B3: Key terms and supporting IAQG documents. Paraphrased for field use; the licensed standard is the only authority.
B5: Key terms (AS9100D clause 3, paraphrased)
B6: Term | C6: Meaning | D6: Reference
B7: Counterfeit part | C7: A part that is an unauthorized copy, imitation, substitute or modification and is knowingly presented as a genuine part from an original or authorized manufacturer. Includes false marking, grade, serial number, date code, documentation or performance claims. | D7: Clause 3.1
B8: Critical items | C8: Functions, parts, software, characteristics or processes with a significant effect on providing and using the product (safety, performance, form, fit, function, producibility, service life) that need specific actions to be managed. Examples: safety critical, fracture critical and mission critical items, key characteristics. | D8: Clause 3.2
B9: Key characteristic | C9: A feature whose variation has a significant effect on fit, form, function, performance, service life or producibility and that needs specific action to control the variation. | D9: Clause 3.3
B10: Product safety | C10: The state in which the product can perform its intended function without unacceptable risk of harm to people or damage to property. | D10: Clause 3.4
B11: Special requirements | C11: Requirements, set by the customer or the organization, that carry a high risk of not being met (for example because of complexity, limited experience, immature processes or performance at the limit of capability) and therefore go into the operational risk process. | D11: Clause 3.5
B13: Supporting IAQG documents (relationship table in the standard's Annex C)
B14: Document | C14: Topic | D14: Related clauses
B15: 9101 | C15: Audit requirements: preparation, execution and reporting of audits to the 9100 series | D15: 4.4, 9.2
B16: 9102 | C16: First article inspection requirements | D16: 8.4.2, 8.5.1.3
B17: 9103 | C17: Variation management of key characteristics | D17: 8.1, 8.3.5, 8.4.3, 8.5.1
B18: 9107 | C18: Direct delivery authorization guidance | D18: 8.6
B19: 9114 | C19: Direct ship guidance (shipment from a provider to the customer) | D19: 8.6
B20: 9115 | C20: Deliverable software requirements, used with 9100 | D20: All clauses
B21: 9116 | C21: Notice of change requirements | D21: 8.3.6, 8.4.3, 8.5.6
B22: 9131 | C22: Nonconformance documentation: data definition and documentation | D22: 8.7, 10.2
B23: 9132 | C23: Data matrix quality requirements for parts marking | D23: 8.5.2
B24: 9133 | C24: Qualification procedure for aerospace standard products | D24: 8.4.2, 8.6
B25: 9134 | C25: Supply chain risk management guideline | D25: 8.4.1
... B27: 9110 / 9120 | C27: QMS requirements for aviation maintenance organizations (9110) and for distributors (9120): sister standards to 9100 | D27: Scope selection
B29: Document numbers, titles and relationships are as listed in AS9100 Rev D. Later revisions of the 9100 series and of these documents may differ; verify against the current IAQG standards register.

Sheet AI Use Guide
B2: Using AI Safely in an Audit Workflow
B4: Where AI helps
B5: Draft questions | C5: Generate additional audit questions tailored to a process or product.
B6: Evidence lists | C6: Turn a clause into a request-for-evidence list to send before the audit.
B7: Finding wording | C7: Draft clear, factual finding statements from your raw notes (you verify every word).
B8: Summaries | C8: Summarize long procedures or prior reports to prepare faster.
B9: Guardrails
B10: Confidentiality | C10: Do not enter client names, part numbers, drawings, contract terms, customer proprietary data or export-controlled technical data (for example ITAR or EAR). Sanitize first ("Client A", "Part X").
B11: Verification | C11: AI can misstate requirements, and AS9100D differs from ISO 9001 in many small ways. Check every clause reference against the licensed standard.
B12: Judgment | C12: Classification of findings (minor or major) and conclusions remain the auditor's decision.
B13: Record | C13: Note in the audit file where AI assisted drafting.
B14: Starter prompts
B15: Evidence request | C15: "Act as an AS9100D auditor. For clause 8.4.1.1, list the documents and records I should request from a small machining supplier about its external provider approval register. Use generic placeholders; no client data."
B16: Finding draft | C16: "Rewrite these notes as a factual nonconformity statement: requirement, evidence observed, gap. Notes: [sanitized notes]."
B17: Interview prep | C17: "Suggest 8 open-ended interview questions for a quality engineer about first article inspection triggers (clause 8.5.1.3), avoiding leading questions."
B18: Root cause review | C18: "Here is a sanitized corrective action summary. Identify where the root cause analysis is shallow and suggest questions to test whether human factors were considered."
B20: © 2026 Cristian La Bella Consulting. All rights reserved. | cristianlabella.com
